odoo/addons/account_payment_unece/README.rst
odoo/addons/account_payment_unece/__init__.py
odoo/addons/account_payment_unece/__manifest__.py
odoo/addons/account_payment_unece/data/account_payment_method.xml
odoo/addons/account_payment_unece/data/unece.xml
odoo/addons/account_payment_unece/i18n/account_payment_unece.pot
odoo/addons/account_payment_unece/i18n/fr.po
odoo/addons/account_payment_unece/i18n/it.po
odoo/addons/account_payment_unece/migrations/12.0.1.0.0/openupgrade_analysis.txt
odoo/addons/account_payment_unece/migrations/12.0.1.0.0/openupgrade_analysis_work.txt
odoo/addons/account_payment_unece/migrations/12.0.1.0.0/post-migration.py
odoo/addons/account_payment_unece/models/__init__.py
odoo/addons/account_payment_unece/models/account_payment_method.py
odoo/addons/account_payment_unece/models/unece_code_list.py
odoo/addons/account_payment_unece/readme/CONFIGURE.rst
odoo/addons/account_payment_unece/readme/CONTRIBUTORS.rst
odoo/addons/account_payment_unece/readme/DESCRIPTION.rst
odoo/addons/account_payment_unece/static/description/icon.png
odoo/addons/account_payment_unece/static/description/index.html
odoo/addons/account_payment_unece/views/account_payment_method.xml
odoo12_addon_account_payment_unece-12.0.1.0.0.99.dev14.dist-info/METADATA
odoo12_addon_account_payment_unece-12.0.1.0.0.99.dev14.dist-info/WHEEL
odoo12_addon_account_payment_unece-12.0.1.0.0.99.dev14.dist-info/top_level.txt
odoo12_addon_account_payment_unece-12.0.1.0.0.99.dev14.dist-info/RECORD
